trueskillthroughtime/__init__.py
trueskillthroughtime-1.1.0.dist-info/LICENSE
trueskillthroughtime-1.1.0.dist-info/METADATA
trueskillthroughtime-1.1.0.dist-info/WHEEL
trueskillthroughtime-1.1.0.dist-info/top_level.txt
trueskillthroughtime-1.1.0.dist-info/RECORD
