Metadata-Version: 2.1
Name: trueskillthroughtime
Version: 1.1.0
Summary: The temporal learning estimator: Individual learning curves with reliable initial estimates and guaranteed comparability between distant estimates.
Home-page: https://github.com/glandfried/TrueSkillThroughTime.py/
Download-URL: https://github.com/glandfried/TrueSkillThroughTime.py/archive/refs/tags/v1.1.0.tar.gz
Author: Gustavo Landfried
Author-email: gustavolandfried@gmail.com
Classifier: Development Status :: 4 - Beta
Classifier: Programming Language :: Python :: 3
Classifier: License :: OSI Approved :: BSD License
Classifier: Operating System :: OS Independent
License-File: LICENSE
